KiticaLibrary/KiticaLibrary.py
KiticaLibrary/__init__.py
KiticaLibrary/errors.py
KiticaLibrary/version.py
rf_kiticalibrary-1.0.dist-info/LICENSE
rf_kiticalibrary-1.0.dist-info/METADATA
rf_kiticalibrary-1.0.dist-info/WHEEL
rf_kiticalibrary-1.0.dist-info/top_level.txt
rf_kiticalibrary-1.0.dist-info/RECORD
