Metadata-Version: 2.1
Name: rf-kiticalibrary
Version: 1.0
Summary: Test Library for Devicepool Support.
Home-page: https://github.com/MainSystemDev/kitica
Author: Joshua Kim Rivera
Author-email: joshua.rivera@mnltechnology.com
License: Type license() to see the full license text
Platform: any
Classifier: Development Status :: 4 - Beta
Classifier: License :: OSI Approved :: MIT License
Classifier: Operating System :: OS Independent
Classifier: Programming Language :: Python :: 3
Classifier: Topic :: Software Development :: Testing
Classifier: Framework :: Robot Framework
Classifier: Framework :: Robot Framework :: Library
Requires-Dist: requests (==2.22.0)
Requires-Dist: robotframework (==3.1.2)
Requires-Dist: robotlibcore-temp (==1.0.2)
